README.md
setup.py
bin/acquire
bin/fastfix
fastfix/__init__.py
fastfix/acquisition.py
fastfix/angle.py
fastfix/bit_error_rate.py
fastfix/ephemerides_proxy.py
fastfix/ephemeris.py
fastfix/fastfix.py
fastfix/file_cache.py
fastfix/forward_map.py
fastfix/gps_time.py
fastfix/load_data.py
fastfix/location.py
fastfix/mcmc.py
fastfix/tag_acquire.py
fastfix/test_ephem.py
fastfix/test_gps_time.py
fastfix/test_location.py
fastfix/utc.py
fastfix/util.py
fastfix.egg-info/PKG-INFO
fastfix.egg-info/SOURCES.txt
fastfix.egg-info/dependency_links.txt
fastfix.egg-info/requires.txt
fastfix.egg-info/top_level.txt