Metadata-Version: 2.1
Name: fastfix
Version: 0.1.0b3
Summary: FastFix Positioning
Home-page: http://github.com/elec-otago/fastfix
Author: Tim Molteno
Author-email: tim@elec.ac.nz
License: GPLv3
Platform: UNKNOWN
Classifier: Development Status :: 4 - Beta
Classifier: Topic :: Scientific/Engineering
Classifier: License :: OSI Approved :: GNU General Public License v3 (GPLv3)
Classifier: Programming Language :: Python :: 3
Classifier: Programming Language :: Python :: 3.5
Classifier: Programming Language :: Python :: 3.6
Classifier: Programming Language :: Python :: 3.7
Classifier: Intended Audience :: Science/Research
